autotwin_gmglib.py
default.json
autotwin_gmglib-0.1.17.dist-info/LICENSE
autotwin_gmglib-0.1.17.dist-info/METADATA
autotwin_gmglib-0.1.17.dist-info/WHEEL
autotwin_gmglib-0.1.17.dist-info/RECORD
